ioa_observe/__init__.py
ioa_observe/sdk/__init__.py
ioa_observe/sdk/instruments.py
ioa_observe/sdk/telemetry.py
ioa_observe/sdk/version.py
ioa_observe/sdk/client/__init__.py
ioa_observe/sdk/client/client.py
ioa_observe/sdk/client/http.py
ioa_observe/sdk/config/__init__.py
ioa_observe/sdk/connectors/__init__.py
ioa_observe/sdk/connectors/slim.py
ioa_observe/sdk/decorators/__init__.py
ioa_observe/sdk/decorators/base.py
ioa_observe/sdk/decorators/helpers.py
ioa_observe/sdk/decorators/util.py
ioa_observe/sdk/instrumentations/__init__.py
ioa_observe/sdk/instrumentations/a2a.py
ioa_observe/sdk/instrumentations/mcp.py
ioa_observe/sdk/instrumentations/nats.py
ioa_observe/sdk/instrumentations/slim.py
ioa_observe/sdk/logging/__init__.py
ioa_observe/sdk/logging/logging.py
ioa_observe/sdk/metrics/__init__.py
ioa_observe/sdk/metrics/agent.py
ioa_observe/sdk/metrics/metrics.py
ioa_observe/sdk/metrics/agents/__init__.py
ioa_observe/sdk/metrics/agents/agent_connections.py
ioa_observe/sdk/metrics/agents/availability.py
ioa_observe/sdk/metrics/agents/heuristics.py
ioa_observe/sdk/metrics/agents/recovery_tracker.py
ioa_observe/sdk/metrics/agents/tool_call_tracker.py
ioa_observe/sdk/metrics/agents/tracker.py
ioa_observe/sdk/tracing/__init__.py
ioa_observe/sdk/tracing/content_allow_list.py
ioa_observe/sdk/tracing/context_manager.py
ioa_observe/sdk/tracing/context_utils.py
ioa_observe/sdk/tracing/manual.py
ioa_observe/sdk/tracing/tracing.py
ioa_observe/sdk/tracing/transform_span.py
ioa_observe/sdk/utils/__init__.py
ioa_observe/sdk/utils/const.py
ioa_observe/sdk/utils/in_memory_span_exporter.py
ioa_observe/sdk/utils/json_encoder.py
ioa_observe/sdk/utils/package_check.py
ioa_observe_sdk-1.0.25.dist-info/licenses/LICENSE.md
ioa_observe_sdk-1.0.25.dist-info/METADATA
ioa_observe_sdk-1.0.25.dist-info/WHEEL
ioa_observe_sdk-1.0.25.dist-info/top_level.txt
ioa_observe_sdk-1.0.25.dist-info/RECORD
