Metadata-Version: 2.4
Name: ioa-observe-sdk
Version: 1.0.25
Summary: IOA Observability SDK
License-Expression: Apache-2.0
Requires-Python: >=3.10
License-File: LICENSE.md
Requires-Dist: colorama==0.4.6
Requires-Dist: requests>=2.32.3
Requires-Dist: opentelemetry-api==1.37.0
Requires-Dist: opentelemetry-distro
Requires-Dist: opentelemetry-exporter-otlp==1.37.0
Requires-Dist: opentelemetry-exporter-otlp-proto-common==1.37.0
Requires-Dist: opentelemetry-exporter-otlp-proto-grpc==1.37.0
Requires-Dist: opentelemetry-exporter-otlp-proto-http==1.37.0
Requires-Dist: opentelemetry-instrumentation
Requires-Dist: opentelemetry-instrumentation-logging==0.58b0
Requires-Dist: opentelemetry-instrumentation-openai==0.43.1
Requires-Dist: opentelemetry-instrumentation-llamaindex==0.43.1
Requires-Dist: opentelemetry-instrumentation-ollama==0.43.1
Requires-Dist: opentelemetry-instrumentation-anthropic==0.43.1
Requires-Dist: opentelemetry-instrumentation-langchain==0.43.1
Requires-Dist: opentelemetry-instrumentation-bedrock==0.43.1
Requires-Dist: opentelemetry-instrumentation-cohere==0.43.1
Requires-Dist: opentelemetry-instrumentation-crewai==0.43.1
Requires-Dist: opentelemetry-instrumentation-google-generativeai==0.43.1
Requires-Dist: opentelemetry-instrumentation-groq==0.43.1
Requires-Dist: opentelemetry-instrumentation-mistralai==0.43.1
Requires-Dist: opentelemetry-instrumentation-requests==0.58b0
Requires-Dist: opentelemetry-instrumentation-sagemaker==0.43.1
Requires-Dist: opentelemetry-instrumentation-threading==0.58b0
Requires-Dist: opentelemetry-instrumentation-together==0.43.1
Requires-Dist: opentelemetry-instrumentation-transformers==0.43.1
Requires-Dist: opentelemetry-instrumentation-urllib3==0.58b0
Requires-Dist: opentelemetry-instrumentation-vertexai==0.43.1
Requires-Dist: opentelemetry-proto==1.37.0
Requires-Dist: opentelemetry-sdk==1.37.0
Requires-Dist: opentelemetry-semantic-conventions==0.58b0
Requires-Dist: opentelemetry-semantic-conventions-ai>=0.4.11
Requires-Dist: opentelemetry-util-http==0.58b0
Requires-Dist: langgraph>=0.3.2
Requires-Dist: langchain>=0.3.19
Requires-Dist: langchain-openai>=0.3.8
Requires-Dist: llama-index>=0.12.34
Requires-Dist: pytest
Requires-Dist: pytest-vcr
Dynamic: license-file
